kattention/__init__.py
kattention/layers/__init__.py
kattention/layers/multi_head_attention.py
kattention/layers/self_attention.py
kattention/layers/transformer.py
kattention/viz/__init__.py
kattention/viz/utils.py
kattention-0.1.2.dist-info/LICENSE
kattention-0.1.2.dist-info/METADATA
kattention-0.1.2.dist-info/WHEEL
kattention-0.1.2.dist-info/top_level.txt
kattention-0.1.2.dist-info/RECORD
