Metadata-Version: 2.1
Name: kattention
Version: 0.1.2
Summary: Package implementing different attention mechanisms as tf.keras layers
Home-page: https://github.com/sofienealouini/kattention
Author: Sofiene ALOUINI
Author-email: sofiene.alouini@gmail.com
License: UNKNOWN
Platform: UNKNOWN
Classifier: Programming Language :: Python :: 3
Classifier: License :: OSI Approved :: MIT License
Classifier: Operating System :: OS Independent
Requires-Python: >=3.6
Requires-Dist: tensorflow (>=2.2)
